pylsoFoam/__init__.py
pylsoFoam/clean.py
pylsoFoam/foam.py
pylsoFoam/py.typed
pylsoFoam/utils.py
pylsoFoam/vector.py
pylso_foam-0.1.0.dist-info/LICENSE
pylso_foam-0.1.0.dist-info/WHEEL
pylso_foam-0.1.0.dist-info/METADATA
pylso_foam-0.1.0.dist-info/RECORD
