Metadata-Version: 2.1
Name: pylso-foam
Version: 0.1.0
Summary: Python Large Scale Orchestrator for OpenFOAM computations.
License: Apache-2.0
Author: Johan Hidding
Author-email: j.hidding@esciencecenter.nl
Requires-Python: >=3.9,<3.11
Classifier: License :: OSI Approved :: Apache Software License
Classifier: Programming Language :: Python :: 3
Classifier: Programming Language :: Python :: 3.10
Classifier: Programming Language :: Python :: 3.9
Requires-Dist: PyFoam (>=2022.9,<2023.0)
Requires-Dist: argh (>=0.26.2,<0.27.0)
Requires-Dist: byteparsing (>=0.1.2,<0.2.0)
Requires-Dist: numpy (>=1.23.4,<2.0.0)
